{
  "name": "plan_with_memory",
  "description": "HTN planning augmented with holographic memory as a ReBAC tuple store. Queries stored facts to hydrate the planner's capability state, runs the planner, then stores the result for future algebraic recall.",
  "parameters": {
    "type": "object",
    "properties": {
      "domain": {
        "type": "string",
        "enum": ["simple_travel", "blocks_world", "rescue", "robosub", "healthcare", "temporal_travel", "entity_capabilities", "job_shop_scheduling", "gltf_interactivity"],
        "description": "Planning domain to use."
      },
      "task": {
        "type": "string",
        "description": "Preset task name (domain-specific)."
      },
      "tasks": {
        "type": "array",
        "items": { "type": "array" },
        "description": "Custom task list."
      },
      "state": {
        "type": "object",
        "description": "Custom initial state (will be augmented from memory)."
      },
      "problem": {
        "type": "string",
        "description": "Named problem variant (domain-specific, e.g. '1a', '2b')."
      },
      "use_memory": {
        "type": "boolean",
        "description": "Whether to hydrate capability state from memory. Default: true."
      },
      "store_result": {
        "type": "boolean",
        "description": "Whether to store plan result back into memory. Default: true."
      },
      "memory_trust_threshold": {
        "type": "number",
        "description": "Minimum trust score for memory facts used in planning. Default: 0.5."
      }
    },
    "required": ["domain"]
  }
}
